banner_donguk777/__init__.py
banner_donguk777/banner.py
banner_DONGUK777-0.3.1.dist-info/METADATA
banner_DONGUK777-0.3.1.dist-info/WHEEL
banner_DONGUK777-0.3.1.dist-info/entry_points.txt
banner_DONGUK777-0.3.1.dist-info/top_level.txt
banner_DONGUK777-0.3.1.dist-info/RECORD
