Metadata-Version: 2.1
Name: banner_DONGUK777
Version: 0.3.1
Summary: Default template for PDM package
Author-email: DONGUK777 <kimdongyork@gmail.com>
License: MIT
Requires-Python: >=3.9
Requires-Dist: pyfiglet >=1.0.2
